qd2_orchestrator/__init__.py
qd2_orchestrator/cli.py
qd2_orchestrator/orchestratorlib.py
qd2_orchestrator/rabbit_mq_installation.sh
qd2_orchestrator-2.1.2.dist-info/METADATA
qd2_orchestrator-2.1.2.dist-info/WHEEL
qd2_orchestrator-2.1.2.dist-info/entry_points.txt
qd2_orchestrator-2.1.2.dist-info/RECORD
