Metadata-Version: 2.4
Name: qd2_orchestrator
Version: 2.1.2
Summary: The Quditto orchestrator
Author-email: Blanca Lopez <blanca.lopez@imdea.org>, Angela Diaz <angela.diaz@imdea.org>, Javier Perez <javier.perez@imdea.org>
Requires-Python: >=3.8
Requires-Dist: ansible
Requires-Dist: ansible-core
Requires-Dist: ansible-runner
Requires-Dist: click
Requires-Dist: pyyaml
